nonebot_plugin_matchreminder-1.0.4.dist-info/METADATA
nonebot_plugin_matchreminder-1.0.4.dist-info/WHEEL
nonebot_plugin_matchreminder-1.0.4.dist-info/licenses/LICENSE
nonebot_plugin_matchreminder/__init__.py
nonebot_plugin_matchreminder/config.py
nonebot_plugin_matchreminder/data_source.py
nonebot_plugin_matchreminder-1.0.4.dist-info/RECORD
