Metadata-Version: 2.1
Name: nonebot_plugin_matchreminder
Version: 1.0.4
Summary: 定时设置算法比赛赛前提醒，提醒群友别错过比赛，查询codeforce，atc，牛客比赛消息
Author-Email: zhuhiki <z1607258120@163.com>
License: MIT
Requires-Python: >=3.9
Requires-Dist: lxml>=4.9.3
Requires-Dist: bs4>=0.0.1
Requires-Dist: nonebot2>=2.0.1
Requires-Dist: httpx>=0.23.3
Requires-Dist: nonebot-adapter-onebot>=2.1.5
Requires-Dist: fake-useragent>=1.1.3
Requires-Dist: asyncio>=3.4.3
